xbmini/__init__.py
xbmini/cli.py
xbmini/heading_parser.py
xbmini/log_parser.py
xbmini/trim.py
xbmini_py-0.5.1.dist-info/METADATA
xbmini_py-0.5.1.dist-info/WHEEL
xbmini_py-0.5.1.dist-info/entry_points.txt
xbmini_py-0.5.1.dist-info/licenses/LICENSE
xbmini_py-0.5.1.dist-info/RECORD
