Metadata-Version: 2.4
Name: xbmini-py
Version: 0.5.1
Summary: Python Toolkit for the GCDC HAM
Project-URL: Homepage, https://github.com/sco1/
Project-URL: Documentation, https://github.com/sco1/xbmini-py/blob/main/README.md
Project-URL: Repository, https://github.com/sco1/xbmini-py
Project-URL: Issues, https://github.com/sco1/xbmini-py/issues
Project-URL: Changelog, https://github.com/sco1/xbmini-py/blob/main/CHANGELOG.md
Author-email: sco1 <sco1.git@gmail.com>
Maintainer-email: sco1 <sco1.git@gmail.com>
License-File: LICENSE
Classifier: Development Status :: 4 - Beta
Classifier: Intended Audience :: Developers
Classifier: License :: OSI Approved :: MIT License
Classifier: Operating System :: OS Independent
Classifier: Programming Language :: Python :: 3 :: Only
Classifier: Programming Language :: Python :: 3.11
Classifier: Programming Language :: Python :: 3.12
Classifier: Programming Language :: Python :: 3.13
Classifier: Typing :: Typed
Requires-Python: >=3.11
Requires-Dist: matplotlib-window~=1.1
Requires-Dist: polars~=1.21
Requires-Dist: sco1-misc~=0.1
Requires-Dist: typer-slim~=0.12
